flask_stupe/__init__.py
flask_stupe/app.py
flask_stupe/auth.py
flask_stupe/config.py
flask_stupe/converters.py
flask_stupe/fields.py
flask_stupe/inputs.py
flask_stupe/json.py
flask_stupe/logging.py
flask_stupe/pagination.py
flask_stupe/request.py
flask_stupe/validation.py
Flask_Stupe-4.3.0.dist-info/LICENSE
Flask_Stupe-4.3.0.dist-info/METADATA
Flask_Stupe-4.3.0.dist-info/WHEEL
Flask_Stupe-4.3.0.dist-info/top_level.txt
Flask_Stupe-4.3.0.dist-info/RECORD
