Metadata-Version: 2.1
Name: Flask-Stupe
Version: 4.3.0
Summary: a.k.a. « Flask on steroids »
Home-page: https://github.com/numberly/flask-stupe
Author: Guillaume Gelin
Author-email: ramnes@1000mercis.com
License: MIT
Platform: any
Classifier: Environment :: Web Environment
Classifier: Intended Audience :: Developers
Classifier: Operating System :: OS Independent
Classifier: Programming Language :: Python
Classifier: Topic :: Internet :: WWW/HTTP :: Dynamic Content
Classifier: Topic :: Software Development :: Libraries :: Python Modules
Requires-Dist: Flask (>=0.11)
